{
    "id": "4cbf7c6d-3f12-4773-8f79-86a2b34c53b3",
    "type": "searchset",
    "timestamp": "2021-12-16T09:02:54.730+00:00",
    "resourceType": "Bundle",
    "total": 1,
    "entry":
    [
        {
            "fullUrl": "https://erp-test.zentral.erp.splitdns.ti-dienste.de/Communication/01eb7d1d-717c-8e60-7579-f906d15cf93e",
            "resource":
            {
                "resourceType": "Communication",
                "meta":
                {
                    "profile":
                    [
                        "https://gematik.de/fhir/StructureDefinition/ErxCommunicationReply|1.1.1"
                    ]
                },
                "basedOn":
                [
                    {
                        "reference": "Task/160.000.000.024.840.33"
                    }
                ],
                "status": "unknown",
                "recipient":
                [
                    {
                        "identifier":
                        {
                            "system": "http://fhir.de/NamingSystem/gkv/kvid-10",
                            "value": "X110400607"
                        }
                    }
                ],
                "payload":
                [
                    {
                        "extension":
                        [
                            {
                                "url": "https://gematik.de/fhir/StructureDefinition/SupplyOptionsType|1.1.1",
                                "extension":
                                [
                                    {
                                        "url": "onPremise",
                                        "valueBoolean": true
                                    },
                                    {
                                        "url": "delivery",
                                        "valueBoolean": true
                                    },
                                    {
                                        "url": "shipment",
                                        "valueBoolean": true
                                    }
                                ]
                            }
                        ],
                        "contentString": "{\"pickUpCodeHR\":\"12344321\",\"info_text\":\"Default Reply Message\",\"pickUpCodeDMC\":\"0123456789abcdefggfedcba9876543210\",\"supplyOptionsType\":\"onPremise\",\"version\":\"1\",\"url\":\"\"}"
                    }
                ],
                "sender":
                {
                    "identifier":
                    {
                        "value": "3-SMC-B-Testkarte-883110000129068",
                        "system": "https://gematik.de/fhir/NamingSystem/TelematikID"
                    }
                },
                "sent": "2021-12-16T08:56:16.444+00:00",
                "id": "01eb7d1d-717c-8e60-7579-f906d15cf93e",
                "received": "2021-12-16T08:56:20.000+00:00"
            },
            "search":
            {
                "mode": "match"
            }
        }
    ],
    "link":
    [
        {
            "relation": "next",
            "url": "https://erp-test.zentral.erp.splitdns.ti-dienste.de/Communication?_count=50&__offset=50"
        },
        {
            "relation": "self",
            "url": "https://erp-test.zentral.erp.splitdns.ti-dienste.de/Communication"
        }
    ]
}